[
  {
    "rank": 1,
    "id": "27000534",
    "name": "洛二神",
    "url": "https://tabelog.com/osaka/A2701/A270103/27000534/",
    "image": "https://tblg.k-img.com/restaurant/images/Rvw/66799/640x640_rect_66799181.jpg",
    "address": "大阪府大阪市北区浪花町4-22 藤ビル　１Ｆ",
    "rating": 3.74,
    "ratingCount": 1625,
    "lat": 34.70754399797907,
    "lng": 135.51055468753253,
    "year": 2025,
    "award": "2025 ・ 百名店 ラーメン 大阪",
    "genre": "ラーメン"
  },
  {
    "rank": 2,
    "id": "27104891",
    "name": "麦と麺助",
    "url": "https://tabelog.com/osaka/A2701/A270101/27104891/",
    "image": "https://tblg.k-img.com/restaurant/images/Rvw/142804/640x640_rect_142804940.jpg",
    "address": "大阪府大阪市北区豊崎3-4-12",
    "rating": 3.83,
    "ratingCount": 2390,
    "lat": 34.71134433716793,
    "lng": 135.50001967641657,
    "year": 2025,
    "award": "2025 ・ 百名店 ラーメン 大阪",
    "genre": "ラーメン"
  },
  {
    "rank": 3,
    "id": "27084317",
    "name": "馬鹿坊",
    "url": "https://tabelog.com/osaka/A2701/A270101/27084317/",
    "image": "https://tblg.k-img.com/restaurant/images/Rvw/365861/640x640_rect_92d3a7e63f9b28eedac8caa88d78e9cf.jpg",
    "address": "大阪府大阪市北区浮田1-4-10",
    "rating": 3.7,
    "ratingCount": 976,
    "lat": 34.70883919797746,
    "lng": 135.50806250754738,
    "year": 2025,
    "award": "2025 ・ 百名店 ラーメン 大阪",
    "genre": "ラーメン"
  },
  {
    "rank": 4,
    "id": "27117612",
    "name": "自家製麺 つきよみ",
    "url": "https://tabelog.com/osaka/A2701/A270307/27117612/",
    "image": "https://tblg.k-img.com/restaurant/images/Rvw/360052/640x640_rect_5deafdeea51df5131c2b5f1ef9b894dc.jpg",
    "address": "大阪府大阪市東淀川区豊新5-11-4",
    "rating": 3.71,
    "ratingCount": 996,
    "lat": 34.74623195796287,
    "lng": 135.5368256179049,
    "year": 2025,
    "award": "2025 ・ 百名店 ラーメン 大阪",
    "genre": "ラーメン"
  },
  {
    "rank": 5,
    "id": "27100567",
    "name": "塩々",
    "url": "https://tabelog.com/osaka/A2701/A270101/27100567/",
    "image": "https://tblg.k-img.com/restaurant/images/Rvw/87546/640x640_rect_87546516.jpg",
    "address": "大阪府大阪市福島区玉川1-2-51",
    "rating": 3.69,
    "ratingCount": 709,
    "lat": 34.68975173717645,
    "lng": 135.4836939762099,
    "year": 2025,
    "award": "2025 ・ 百名店 ラーメン 大阪",
    "genre": "ラーメン"
  },
  {
    "rank": 6,
    "id": "27101092",
    "name": "ラーメン家 あかぎ",
    "url": "https://tabelog.com/osaka/A2701/A270307/27101092/",
    "image": "https://tblg.k-img.com/restaurant/images/Rvw/364944/640x640_rect_dcf01719555c65af694c03ddd5c3a978.jpg",
    "address": "大阪府大阪市東淀川区瑞光2-2-21",
    "rating": 3.72,
    "ratingCount": 1202,
    "lat": 34.74988622796061,
    "lng": 135.5370153979417,
    "year": 2025,
    "award": "2025 ・ 百名店 ラーメン 大阪",
    "genre": "ラーメン"
  },
  {
    "rank": 7,
    "id": "27103068",
    "name": "麺や 清流",
    "url": "https://tabelog.com/osaka/A2707/A270703/27103068/",
    "image": "https://tblg.k-img.com/restaurant/images/Rvw/137185/640x640_rect_137185305.jpg",
    "address": "大阪府東大阪市小若江1-4-3",
    "rating": 3.7,
    "ratingCount": 983,
    "lat": 34.65107833803725,
    "lng": 135.58062924691305,
    "year": 2025,
    "award": "2025 ・ 百名店 ラーメン 大阪",
    "genre": "ラーメン"
  },
  {
    "rank": 8,
    "id": "27118157",
    "name": "らーめん これこれ",
    "url": "https://tabelog.com/osaka/A2706/A270602/27118157/",
    "image": "https://tblg.k-img.com/restaurant/images/Rvw/338818/640x640_rect_ecfe8b39a69b9a360eacda00dd16b59d.jpg",
    "address": "大阪府吹田市江坂町1-20-30 キャロル江坂 1F",
    "rating": 3.69,
    "ratingCount": 1471,
    "lat": 34.75832480794344,
    "lng": 135.49992738805292,
    "year": 2025,
    "award": "2025 ・ 百名店 ラーメン 大阪",
    "genre": "ラーメン"
  },
  {
    "rank": 9,
    "id": "27060153",
    "name": "手打ち麺 やす田",
    "url": "https://tabelog.com/osaka/A2701/A270301/27060153/",
    "image": "https://tblg.k-img.com/restaurant/images/Rvw/366131/640x640_rect_450ef6f3d78d2298b787bb0da115c900.jpg",
    "address": "大阪府大阪市東淀川区東中島1-21-2 新大阪ハイツ106号",
    "rating": 3.74,
    "ratingCount": 1278,
    "lat": 34.73296330796085,
    "lng": 135.50402665779387,
    "year": 2025,
    "award": "2025 ・ 百名店 ラーメン 大阪",
    "genre": "ラーメン"
  },
  {
    "rank": 10,
    "id": "27075534",
    "name": "縁乃助商店",
    "url": "https://tabelog.com/osaka/A2701/A270307/27075534/",
    "image": "https://tblg.k-img.com/restaurant/images/Rvw/361751/640x640_rect_1780aeebab338fc5fe8989e2c362d885.jpg",
    "address": "大阪府大阪市東淀川区淡路4-9-5",
    "rating": 3.66,
    "ratingCount": 933,
    "lat": 34.740140037155044,
    "lng": 135.51694227669552,
    "year": 2025,
    "award": "2025 ・ 百名店 ラーメン 大阪",
    "genre": "ラーメン"
  },
  {
    "rank": 11,
    "id": "27097061",
    "name": "らぁ麺屋 はりねずみ",
    "url": "https://tabelog.com/osaka/A2706/A270604/27097061/",
    "image": "https://tblg.k-img.com/restaurant/images/Rvw/315943/640x640_rect_96f1e9e129d29009c5a2ac36fe7420f0.jpg",
    "address": "大阪府高槻市野見町4-6 1F",
    "rating": 3.7,
    "ratingCount": 708,
    "lat": 34.84558498792579,
    "lng": 135.61854509885117,
    "year": 2025,
    "award": "2025 ・ 百名店 ラーメン 大阪",
    "genre": "ラーメン"
  },
  {
    "rank": 12,
    "id": "27087256",
    "name": "中華蕎麦 葛",
    "url": "https://tabelog.com/osaka/A2701/A270106/27087256/",
    "image": "https://tblg.k-img.com/restaurant/images/Rvw/51170/640x640_rect_51170732.jpg",
    "address": "大阪府大阪市西区阿波座1-12-21 喜多ビル 1F",
    "rating": 3.75,
    "ratingCount": 2133,
    "lat": 34.68136643237469,
    "lng": 135.49499925033336,
    "year": 2025,
    "award": "2025 ・ 百名店 ラーメン 大阪",
    "genre": "ラーメン"
  },
  {
    "rank": 13,
    "id": "27042868",
    "name": "麺や拓",
    "url": "https://tabelog.com/osaka/A2701/A270105/27042868/",
    "image": "https://tblg.k-img.com/restaurant/images/Rvw/40546/640x640_rect_40546423.jpg",
    "address": "大阪府大阪市西区北堀江3-5-2",
    "rating": 3.69,
    "ratingCount": 1127,
    "lat": 34.67302061799453,
    "lng": 135.49022585719806,
    "year": 2025,
    "award": "2025 ・ 百名店 ラーメン 大阪",
    "genre": "ラーメン"
  },
  {
    "rank": 14,
    "id": "27058993",
    "name": "烈志笑魚油 麺香房 三く",
    "url": "https://tabelog.com/osaka/A2701/A270108/27058993/",
    "image": "https://tblg.k-img.com/restaurant/images/Rvw/170735/640x640_rect_f748b95d2c6ce85bd62df5e69df3a170.jpg",
    "address": "大阪府大阪市福島区福島2-6-5 AKパレス 1F",
    "rating": 3.73,
    "ratingCount": 2570,
    "lat": 34.693763387979985,
    "lng": 135.4859225274106,
    "year": 2025,
    "award": "2025 ・ 百名店 ラーメン 大阪",
    "genre": "ラーメン"
  },
  {
    "rank": 15,
    "id": "27050827",
    "name": "ラーメン人生JET",
    "url": "https://tabelog.com/osaka/A2701/A270108/27050827/",
    "image": "https://tblg.k-img.com/restaurant/images/Rvw/362387/640x640_rect_663458f1a19de120a35f0b502d50ba8e.jpg",
    "address": "大阪府大阪市福島区福島7-12-2",
    "rating": 3.76,
    "ratingCount": 3727,
    "lat": 34.698617647977116,
    "lng": 135.48660799745917,
    "year": 2025,
    "award": "2025 ・ 百名店 ラーメン 大阪",
    "genre": "ラーメン"
  },
  {
    "rank": 16,
    "id": "27007898",
    "name": "塩ラーメン あす流",
    "url": "https://tabelog.com/osaka/A2706/A270604/27007898/",
    "image": "https://tblg.k-img.com/restaurant/images/Rvw/364852/640x640_rect_15f9d5ad1efda50767fce7b1c798e144.jpg",
    "address": "大阪府高槻市紺屋町8-30 ２Ｆ",
    "rating": 3.7,
    "ratingCount": 967,
    "lat": 34.84916634792338,
    "lng": 135.61810097888767,
    "year": 2025,
    "award": "2025 ・ 百名店 ラーメン 大阪",
    "genre": "ラーメン"
  },
  {
    "rank": 17,
    "id": "27015801",
    "name": "とんぴととりの光龍益",
    "url": "https://tabelog.com/osaka/A2701/A270304/27015801/",
    "image": "https://tblg.k-img.com/restaurant/images/Rvw/61033/640x640_rect_61033181.jpg",
    "address": "大阪府大阪市都島区中野町5-9-5",
    "rating": 3.72,
    "ratingCount": 1071,
    "lat": 34.705643497984276,
    "lng": 135.52310324750454,
    "year": 2025,
    "award": "2025 ・ 百名店 ラーメン 大阪",
    "genre": "ラーメン"
  },
  {
    "rank": 18,
    "id": "27090343",
    "name": "醤油と貝と麺 そして人と夢",
    "url": "https://tabelog.com/osaka/A2701/A270302/27090343/",
    "image": "https://tblg.k-img.com/restaurant/images/Rvw/362475/640x640_rect_5c5c5cba4cb6bc2a2e61677acadc1e0c.jpg",
    "address": "大阪府大阪市西淀川区柏里3-12-22",
    "rating": 3.66,
    "ratingCount": 837,
    "lat": 34.71339155796164,
    "lng": 135.46749687762178,
    "year": 2025,
    "award": "2025 ・ 百名店 ラーメン 大阪",
    "genre": "ラーメン"
  },
  {
    "rank": 19,
    "id": "27059500",
    "name": "麺屋彩々 昭和町本店",
    "url": "https://tabelog.com/osaka/A2701/A270203/27059500/",
    "image": "https://tblg.k-img.com/restaurant/images/Rvw/74561/640x640_rect_74561707.jpg",
    "address": "大阪府大阪市阿倍野区阪南町1-46-8",
    "rating": 3.7,
    "ratingCount": 1384,
    "lat": 34.633989318027645,
    "lng": 135.5163803267855,
    "year": 2025,
    "award": "2025 ・ 百名店 ラーメン 大阪",
    "genre": "ラーメン"
  },
  {
    "rank": 20,
    "id": "27101904",
    "name": "いかれたヌードル フィッシュトンズ",
    "url": "https://tabelog.com/osaka/A2701/A270201/27101904/",
    "image": "https://tblg.k-img.com/restaurant/images/Rvw/342237/640x640_rect_43c5785d832aef39af637893680302de.jpg",
    "address": "大阪府大阪市西区新町1-25-18 レナジア新町ビル 1F",
    "rating": 3.73,
    "ratingCount": 2109,
    "lat": 34.67630529799398,
    "lng": 135.49506563722784,
    "year": 2025,
    "award": "2025 ・ 百名店 ラーメン 大阪",
    "genre": "ラーメン"
  },
  {
    "rank": 21,
    "id": "27053626",
    "name": "中華そば 無限",
    "url": "https://tabelog.com/osaka/A2701/A270108/27053626/",
    "image": "https://tblg.k-img.com/restaurant/images/Rvw/199777/640x640_rect_06a2d76259eec13f39df2a8be8084fb3.jpg",
    "address": "大阪府大阪市福島区海老江5-5-10",
    "rating": 3.75,
    "ratingCount": 1699,
    "lat": 34.69661133716843,
    "lng": 135.4722094762872,
    "year": 2025,
    "award": "2025 ・ 百名店 ラーメン 大阪",
    "genre": "ラーメン"
  },
  {
    "rank": 22,
    "id": "27002613",
    "name": "博多とんこつ 天神旗",
    "url": "https://tabelog.com/osaka/A2701/A270307/27002613/",
    "image": "https://tblg.k-img.com/restaurant/images/Rvw/348751/640x640_rect_6ba2c89331ab3a7ebdffdb23f59df789.jpg",
    "address": "大阪府大阪市東淀川区上新庄3-19-87",
    "rating": 3.71,
    "ratingCount": 1168,
    "lat": 34.752154247957726,
    "lng": 135.5324793379678,
    "year": 2025,
    "award": "2025 ・ 百名店 ラーメン 大阪",
    "genre": "ラーメン"
  },
  {
    "rank": 23,
    "id": "27093194",
    "name": "麺麓menroku",
    "url": "https://tabelog.com/osaka/A2707/A270702/27093194/",
    "image": "https://tblg.k-img.com/restaurant/images/Rvw/365397/640x640_rect_14ce68253805f67a8e61a195920405e1.jpg",
    "address": "大阪府枚方市大峰元町1-6-30",
    "rating": 3.68,
    "ratingCount": 943,
    "lat": 34.81293336796789,
    "lng": 135.68560393847437,
    "year": 2025,
    "award": "2025 ・ 百名店 ラーメン 大阪",
    "genre": "ラーメン"
  },
  {
    "rank": 24,
    "id": "27117675",
    "name": "RAMEN ガモウスマイル",
    "url": "https://tabelog.com/osaka/A2701/A270305/27117675/",
    "image": "https://tblg.k-img.com/restaurant/images/Rvw/221463/640x640_rect_59e8235e0dbf1ede11d2e8cd6500046a.jpg",
    "address": "大阪府大阪市城東区今福西1-11-5",
    "rating": 3.7,
    "ratingCount": 907,
    "lat": 34.699700827995976,
    "lng": 135.54801218742708,
    "year": 2025,
    "award": "2025 ・ 百名店 ラーメン 大阪",
    "genre": "ラーメン"
  },
  {
    "rank": 25,
    "id": "27084534",
    "name": "西中島 光龍益",
    "url": "https://tabelog.com/osaka/A2701/A270301/27084534/",
    "image": "https://tblg.k-img.com/restaurant/images/Rvw/83832/640x640_rect_83832994.jpg",
    "address": "大阪府大阪市淀川区西中島6-5-2",
    "rating": 3.68,
    "ratingCount": 1000,
    "lat": 34.728528027961424,
    "lng": 135.496986907754,
    "year": 2025,
    "award": "2025 ・ 百名店 ラーメン 大阪",
    "genre": "ラーメン"
  },
  {
    "rank": 26,
    "id": "27083921",
    "name": "らーめん颯人",
    "url": "https://tabelog.com/osaka/A2701/A270103/27083921/",
    "image": "https://tblg.k-img.com/restaurant/images/Rvw/153137/640x640_rect_153137725.jpg",
    "address": "大阪府大阪市北区南森町1-2-2",
    "rating": 3.73,
    "ratingCount": 1486,
    "lat": 34.695626017986484,
    "lng": 135.51004407741252,
    "year": 2025,
    "award": "2025 ・ 百名店 ラーメン 大阪",
    "genre": "ラーメン"
  },
  {
    "rank": 27,
    "id": "27052519",
    "name": "かしや",
    "url": "https://tabelog.com/osaka/A2701/A270406/27052519/",
    "image": "https://tblg.k-img.com/restaurant/images/Rvw/361055/640x640_rect_aea2c94118f8b3896236aef760592c6c.jpg",
    "address": "大阪府大阪市西成区玉出中2-4-21",
    "rating": 3.69,
    "ratingCount": 934,
    "lat": 34.6261718380247,
    "lng": 135.4915548267239,
    "year": 2025,
    "award": "2025 ・ 百名店 ラーメン 大阪",
    "genre": "ラーメン"
  },
  {
    "rank": 28,
    "id": "27091749",
    "name": "麺や 一想",
    "url": "https://tabelog.com/osaka/A2707/A270705/27091749/",
    "image": "https://tblg.k-img.com/restaurant/images/Rvw/60242/640x640_rect_60242238.jpg",
    "address": "大阪府八尾市末広町4-8-21",
    "rating": 3.69,
    "ratingCount": 496,
    "lat": 34.63462965805074,
    "lng": 135.5901968467402,
    "year": 2025,
    "award": "2025 ・ 百名店 ラーメン 大阪",
    "genre": "ラーメン"
  },
  {
    "rank": 29,
    "id": "27105005",
    "name": "中華そば かみなり雲呑",
    "url": "https://tabelog.com/osaka/A2701/A270404/27105005/",
    "image": "https://tblg.k-img.com/restaurant/images/Rvw/106404/640x640_rect_106404006.jpg",
    "address": "大阪府大阪市住吉区長居東3-14-22",
    "rating": 3.68,
    "ratingCount": 860,
    "lat": 34.606949628043964,
    "lng": 135.51369018651428,
    "year": 2025,
    "award": "2025 ・ 百名店 ラーメン 大阪",
    "genre": "ラーメン"
  },
  {
    "rank": 30,
    "id": "27091454",
    "name": "燃えよ麺助",
    "url": "https://tabelog.com/osaka/A2701/A270108/27091454/",
    "image": "https://tblg.k-img.com/restaurant/images/Rvw/64862/640x640_rect_64862990.jpg",
    "address": "大阪府大阪市福島区福島5-12-21",
    "rating": 3.76,
    "ratingCount": 3174,
    "lat": 34.696365747978625,
    "lng": 135.4868678274362,
    "year": 2025,
    "award": "2025 ・ 百名店 ラーメン 大阪",
    "genre": "ラーメン"
  },
  {
    "rank": 31,
    "id": "27083381",
    "name": "らぁめん真",
    "url": "https://tabelog.com/osaka/A2706/A270604/27083381/",
    "image": "https://tblg.k-img.com/restaurant/images/Rvw/360214/640x640_rect_fd469dcdde2237836c40e4fe6ad81d45.jpg",
    "address": "大阪府茨木市駅前1-3-4",
    "rating": 3.69,
    "ratingCount": 734,
    "lat": 34.81634025792686,
    "lng": 135.56357530859432,
    "year": 2025,
    "award": "2025 ・ 百名店 ラーメン 大阪",
    "genre": "ラーメン"
  },
  {
    "rank": 32,
    "id": "27099659",
    "name": "麺や 福はら",
    "url": "https://tabelog.com/osaka/A2701/A270306/27099659/",
    "image": "https://tblg.k-img.com/restaurant/images/Rvw/343475/640x640_rect_d7fc95f266418c43bbae952455328014.jpg",
    "address": "大阪府大阪市生野区新今里5-1-8",
    "rating": 3.73,
    "ratingCount": 1365,
    "lat": 34.66174794802038,
    "lng": 135.54892650704306,
    "year": 2025,
    "award": "2025 ・ 百名店 ラーメン 大阪",
    "genre": "ラーメン"
  },
  {
    "rank": 33,
    "id": "27102601",
    "name": "田中の中華そば",
    "url": "https://tabelog.com/osaka/A2701/A270106/27102601/",
    "image": "https://tblg.k-img.com/restaurant/images/Rvw/363858/640x640_rect_c807dce7394c817a5cfb113f6a594b20.jpg",
    "address": "大阪府大阪市西区靭本町1-18-23 ウルトラビル 1F",
    "rating": 3.73,
    "ratingCount": 1192,
    "lat": 34.684214461694864,
    "lng": 135.49503439406402,
    "year": 2025,
    "award": "2025 ・ 百名店 ラーメン 大阪",
    "genre": "ラーメン"
  },
  {
    "rank": 34,
    "id": "27069769",
    "name": "中華そば うえまち",
    "url": "https://tabelog.com/osaka/A2701/A270204/27069769/",
    "image": "https://tblg.k-img.com/restaurant/images/Rvw/348999/640x640_rect_fb2dff6742bc226095814b8169f8280f.jpg",
    "address": "大阪府大阪市中央区上町A番22号",
    "rating": 3.75,
    "ratingCount": 1869,
    "lat": 34.67691080800187,
    "lng": 135.52103314721575,
    "year": 2025,
    "award": "2025 ・ 百名店 ラーメン 大阪",
    "genre": "ラーメン"
  },
  {
    "rank": 35,
    "id": "27007818",
    "name": "尾道ラーメン 山長",
    "url": "https://tabelog.com/osaka/A2707/A270701/27007818/",
    "image": "https://tblg.k-img.com/restaurant/images/Rvw/360259/640x640_rect_39351cd2ada26a7efec1806fadec9fe4.jpg",
    "address": "大阪府守口市寺内町1-3-5",
    "rating": 3.66,
    "ratingCount": 577,
    "lat": 34.73329331797999,
    "lng": 135.56478311775464,
    "year": 2025,
    "award": "2025 ・ 百名店 ラーメン 大阪",
    "genre": "ラーメン"
  },
  {
    "rank": 36,
    "id": "27105350",
    "name": "中華そば ココカラサキゑ",
    "url": "https://tabelog.com/osaka/A2701/A270301/27105350/",
    "image": "https://tblg.k-img.com/restaurant/images/Rvw/366117/640x640_rect_39b153b819a9a1add5042816fd2c9e62.jpg",
    "address": "大阪府大阪市淀川区西宮原1-7-39",
    "rating": 3.7,
    "ratingCount": 895,
    "lat": 34.73355724795623,
    "lng": 135.4907074978092,
    "year": 2025,
    "award": "2025 ・ 百名店 ラーメン 大阪",
    "genre": "ラーメン"
  },
  {
    "rank": 37,
    "id": "27064537",
    "name": "麺や 紡",
    "url": "https://tabelog.com/osaka/A2706/A270604/27064537/",
    "image": "https://tblg.k-img.com/restaurant/images/Rvw/178854/640x640_rect_e2e12756f8d48836e60da9150845c503.jpg",
    "address": "大阪府茨木市宇野辺2-1-24",
    "rating": 3.71,
    "ratingCount": 1229,
    "lat": 34.8035746371273,
    "lng": 135.55636007730868,
    "year": 2025,
    "award": "2025 ・ 百名店 ラーメン 大阪",
    "genre": "ラーメン"
  },
  {
    "rank": 38,
    "id": "27071670",
    "name": "麺屋 はなぶさ",
    "url": "https://tabelog.com/osaka/A2701/A270106/27071670/",
    "image": "https://tblg.k-img.com/restaurant/images/Rvw/24686/640x640_rect_24686949.jpg",
    "address": "大阪府大阪市中央区本町1-1-4",
    "rating": 3.7,
    "ratingCount": 1077,
    "lat": 34.68386483718844,
    "lng": 135.50961477613225,
    "year": 2025,
    "award": "2025 ・ 百名店 ラーメン 大阪",
    "genre": "ラーメン"
  },
  {
    "rank": 39,
    "id": "27042439",
    "name": "麺元素",
    "url": "https://tabelog.com/osaka/A2701/A270103/27042439/",
    "image": "https://tblg.k-img.com/restaurant/images/Rvw/39410/640x640_rect_39410591.jpg",
    "address": "大阪府大阪市北区天神橋5-2-16",
    "rating": 3.7,
    "ratingCount": 1568,
    "lat": 34.70721111797979,
    "lng": 135.51214363752806,
    "year": 2025,
    "award": "2025 ・ 百名店 ラーメン 大阪",
    "genre": "ラーメン"
  },
  {
    "rank": 40,
    "id": "27074166",
    "name": "極麺 青二犀",
    "url": "https://tabelog.com/osaka/A2706/A270602/27074166/",
    "image": "https://tblg.k-img.com/restaurant/images/Rvw/364279/640x640_rect_d9fc03cd427099acb16beb2812f16d50.jpg",
    "address": "大阪府吹田市末広町21-53",
    "rating": 3.7,
    "ratingCount": 898,
    "lat": 34.765284637144326,
    "lng": 135.53343717693795,
    "year": 2025,
    "award": "2025 ・ 百名店 ラーメン 大阪",
    "genre": "ラーメン"
  },
  {
    "rank": 41,
    "id": "27124383",
    "name": "NEXT□",
    "url": "https://tabelog.com/osaka/A2701/A270202/27124383/",
    "image": "https://tblg.k-img.com/restaurant/images/Rvw/184222/640x640_rect_51a7aef51829c32e48ee8a1fec2c2994.jpg",
    "address": "大阪府大阪市中央区難波千日前9-12 道具屋筋商店街",
    "rating": 3.68,
    "ratingCount": 1157,
    "lat": 34.66425503719895,
    "lng": 135.50350517593844,
    "year": 2025,
    "award": "2025 ・ 百名店 ラーメン 大阪",
    "genre": "ラーメン"
  },
  {
    "rank": 42,
    "id": "27062565",
    "name": "中華そば いぶき",
    "url": "https://tabelog.com/osaka/A2701/A270103/27062565/",
    "image": "https://tblg.k-img.com/restaurant/images/Rvw/67670/640x640_rect_67670563.jpg",
    "address": "大阪府大阪市北区浪花町4-16",
    "rating": 3.7,
    "ratingCount": 1174,
    "lat": 34.70754823717349,
    "lng": 135.50990177637124,
    "year": 2025,
    "award": "2025 ・ 百名店 ラーメン 大阪",
    "genre": "ラーメン"
  },
  {
    "rank": 43,
    "id": "27114537",
    "name": "彩哲",
    "url": "https://tabelog.com/osaka/A2706/A270602/27114537/",
    "image": "https://tblg.k-img.com/restaurant/images/Rvw/148647/640x640_rect_572b9d9f54e750ea8cd69b9a5f282f92.jpg",
    "address": "大阪府吹田市朝日町5-24",
    "rating": 3.68,
    "ratingCount": 518,
    "lat": 34.76191603714373,
    "lng": 135.52486627690996,
    "year": 2025,
    "award": "2025 ・ 百名店 ラーメン 大阪",
    "genre": "ラーメン"
  },
  {
    "rank": 44,
    "id": "27077402",
    "name": "世界一暇なラーメン屋",
    "url": "https://tabelog.com/osaka/A2701/A270102/27077402/",
    "image": "https://tblg.k-img.com/restaurant/images/Rvw/233191/640x640_rect_9dad641e35990732d7d6e5300216c96d.jpg",
    "address": "大阪府大阪市北区中之島3-3-23 中之島ダイビル 2F",
    "rating": 3.69,
    "ratingCount": 2421,
    "lat": 34.69298653717755,
    "lng": 135.49366117623555,
    "year": 2025,
    "award": "2025 ・ 百名店 ラーメン 大阪",
    "genre": "ラーメン"
  },
  {
    "rank": 45,
    "id": "27040392",
    "name": "彩色ラーメンきんせい 高槻本店",
    "url": "https://tabelog.com/osaka/A2706/A270604/27040392/",
    "image": "https://tblg.k-img.com/restaurant/images/Rvw/142514/640x640_rect_142514791.jpg",
    "address": "大阪府高槻市北園町18番1 コーケンビル１Ｆ103号",
    "rating": 3.68,
    "ratingCount": 1543,
    "lat": 34.849933307924026,
    "lng": 135.6216848188929,
    "year": 2025,
    "award": "2025 ・ 百名店 ラーメン 大阪",
    "genre": "ラーメン"
  },
  {
    "rank": 46,
    "id": "27003383",
    "name": "総大醤",
    "url": "https://tabelog.com/osaka/A2701/A270103/27003383/",
    "image": "https://tblg.k-img.com/restaurant/images/Rvw/176760/320x320_rect_0e33c4077a8fd9344650c8c8867032e3.jpg",
    "address": "大阪府大阪市北区浮田2-4-16",
    "rating": 3.73,
    "ratingCount": 2865,
    "lat": 34.71029319797642,
    "lng": 135.5077150075623,
    "year": 2025,
    "award": "2025 ・ 百名店 ラーメン 大阪",
    "genre": "ラーメン"
  },
  {
    "rank": 47,
    "id": "27093539",
    "name": "極汁美麺 umami",
    "url": "https://tabelog.com/osaka/A2707/A270703/27093539/",
    "image": "https://tblg.k-img.com/restaurant/images/Rvw/345491/640x640_rect_14f7d19ece78fe2e7869c2cb47fadb63.jpg",
    "address": "大阪府東大阪市菱屋西3-1-1",
    "rating": 3.7,
    "ratingCount": 991,
    "lat": 34.66395683722298,
    "lng": 135.57833467588299,
    "year": 2025,
    "award": "2025 ・ 百名店 ラーメン 大阪",
    "genre": "ラーメン"
  },
  {
    "rank": 48,
    "id": "27061126",
    "name": "中華そば 閃",
    "url": "https://tabelog.com/osaka/A2701/A270404/27061126/",
    "image": "https://tblg.k-img.com/restaurant/images/Rvw/349865/640x640_rect_4e09cbb3f70701a408c0631f13923cff.jpg",
    "address": "大阪府大阪市住吉区苅田7-6-15",
    "rating": 3.67,
    "ratingCount": 1061,
    "lat": 34.599182918049266,
    "lng": 135.514851626435,
    "year": 2025,
    "award": "2025 ・ 百名店 ラーメン 大阪",
    "genre": "ラーメン"
  },
  {
    "rank": 49,
    "id": "27125673",
    "name": "なにわ麺次郎 然",
    "url": "https://tabelog.com/osaka/A2701/A270101/27125673/",
    "image": "https://tblg.k-img.com/restaurant/images/Rvw/216735/640x640_rect_6cf0da73f41a989ad2e579913f6e2394.jpg",
    "address": "大阪府大阪市北区梅田1-13-13 阪神百貨店梅田本店 B2F",
    "rating": 3.68,
    "ratingCount": 1581,
    "lat": 34.70126875797893,
    "lng": 135.49758409747827,
    "year": 2025,
    "award": "2025 ・ 百名店 ラーメン 大阪",
    "genre": "ラーメン"
  },
  {
    "rank": 50,
    "id": "27085783",
    "name": "麺匠至誠",
    "url": "https://tabelog.com/osaka/A2701/A270201/27085783/",
    "image": "https://tblg.k-img.com/restaurant/images/Rvw/362836/640x640_rect_72a6bb20713156f54f91e29a544a602a.jpg",
    "address": "大阪府大阪市西区新町1-5-7 四ツ橋ビルディング B1F",
    "rating": 3.68,
    "ratingCount": 1001,
    "lat": 34.67564801799492,
    "lng": 135.4966989772201,
    "year": 2025,
    "award": "2025 ・ 百名店 ラーメン 大阪",
    "genre": "ラーメン"
  },
  {
    "rank": 51,
    "id": "27078739",
    "name": "麺匠 而今",
    "url": "https://tabelog.com/osaka/A2707/A270701/27078739/",
    "image": "https://tblg.k-img.com/restaurant/images/Rvw/361239/640x640_rect_140f2ec7b758d8c4009370c483a9e146.jpg",
    "address": "大阪府守口市紅屋町6-16",
    "rating": 3.7,
    "ratingCount": 798,
    "lat": 34.72791983717549,
    "lng": 135.55680027654418,
    "year": 2025,
    "award": "2025 ・ 百名店 ラーメン 大阪",
    "genre": "ラーメン"
  },
  {
    "rank": 52,
    "id": "27001084",
    "name": "カドヤ食堂 総本店",
    "url": "https://tabelog.com/osaka/A2701/A270105/27001084/",
    "image": "https://tblg.k-img.com/restaurant/images/Rvw/355369/640x640_rect_e349e30001d318ebcf301ea0525068a0.jpg",
    "address": "大阪府大阪市西区新町4-16-13 キャピタル西長堀 1F",
    "rating": 3.8,
    "ratingCount": 3527,
    "lat": 34.67610373718517,
    "lng": 135.4838497760719,
    "year": 2025,
    "award": "2025 ・ 百名店 ラーメン 大阪",
    "genre": "ラーメン"
  },
  {
    "rank": 53,
    "id": "27127973",
    "name": "唯一無二のらぁ麺専門店 イ袋ワシづかみ",
    "url": "https://tabelog.com/osaka/A2701/A270203/27127973/",
    "image": "https://tblg.k-img.com/restaurant/images/Rvw/363354/640x640_rect_7d2666477aefc97af5e7175ab2e4efcb.jpg",
    "address": "大阪府大阪市天王寺区四天王寺2-2-7",
    "rating": 3.69,
    "ratingCount": 500,
    "lat": 34.65659583720869,
    "lng": 135.51878167585036,
    "year": 2025,
    "award": "2025 ・ 百名店 ラーメン 大阪",
    "genre": "ラーメン"
  },
  {
    "rank": 54,
    "id": "27116315",
    "name": "上方レインボー",
    "url": "https://tabelog.com/osaka/A2701/A270203/27116315/",
    "image": "https://tblg.k-img.com/restaurant/images/Rvw/366602/640x640_rect_4fba0388063ab38cb7a1466c463508a3.jpg",
    "address": "大阪府大阪市天王寺区勝山4-6-3",
    "rating": 3.71,
    "ratingCount": 812,
    "lat": 34.654800078017466,
    "lng": 135.52590868698903,
    "year": 2025,
    "award": "2025 ・ 百名店 ラーメン 大阪",
    "genre": "ラーメン"
  },
  {
    "rank": 55,
    "id": "27109749",
    "name": "麺処 天川",
    "url": "https://tabelog.com/osaka/A2701/A270105/27109749/",
    "image": "https://tblg.k-img.com/restaurant/images/Rvw/367132/640x640_rect_388ac049b30eab630d8b112e5e1a226b.jpg",
    "address": "大阪府大阪市西区本田1-11-20",
    "rating": 3.68,
    "ratingCount": 515,
    "lat": 34.67671893718329,
    "lng": 135.4791844760814,
    "year": 2025,
    "award": "2025 ・ 百名店 ラーメン 大阪",
    "genre": "ラーメン"
  },
  {
    "rank": 56,
    "id": "27079226",
    "name": "友愛亭",
    "url": "https://tabelog.com/osaka/A2701/A270202/27079226/",
    "image": "https://tblg.k-img.com/restaurant/images/Rvw/366715/640x640_rect_13ffdd3cf6b923e900ca8c15ba31361b.jpg",
    "address": "大阪府大阪市浪速区日本橋4-12-1 旭日旅行ビル 1F",
    "rating": 3.7,
    "ratingCount": 1041,
    "lat": 34.65961468800793,
    "lng": 135.5055788870519,
    "year": 2025,
    "award": "2025 ・ 百名店 ラーメン 大阪",
    "genre": "ラーメン"
  },
  {
    "rank": 57,
    "id": "27093541",
    "name": "ラーメン 哲史",
    "url": "https://tabelog.com/osaka/A2706/A270601/27093541/",
    "image": "https://tblg.k-img.com/restaurant/images/Rvw/366458/640x640_rect_fd94adeb6a5790314d24a94103661c12.jpg",
    "address": "大阪府豊中市小曽根4-9-2",
    "rating": 3.69,
    "ratingCount": 469,
    "lat": 34.75520398794018,
    "lng": 135.48345363803296,
    "year": 2025,
    "award": "2025 ・ 百名店 ラーメン 大阪",
    "genre": "ラーメン"
  },
  {
    "rank": 58,
    "id": "27059047",
    "name": "ラーメン人生JET600",
    "url": "https://tabelog.com/osaka/A2701/A270204/27059047/",
    "image": "https://tblg.k-img.com/restaurant/images/Rvw/53539/640x640_rect_53539081.jpg",
    "address": "大阪府大阪市東成区東小橋1-3-2",
    "rating": 3.71,
    "ratingCount": 1656,
    "lat": 34.67417690800786,
    "lng": 135.53439018717881,
    "year": 2025,
    "award": "2025 ・ 百名店 ラーメン 大阪",
    "genre": "ラーメン"
  },
  {
    "rank": 59,
    "id": "27005006",
    "name": "無鉄砲  大阪店",
    "url": "https://tabelog.com/osaka/A2701/A270206/27005006/",
    "image": "https://tblg.k-img.com/restaurant/images/Rvw/357919/640x640_rect_afcf1faa89749a3e2623ed7cf6522b3e.jpg",
    "address": "大阪府大阪市浪速区戎本町1-5-21 米田ビル　１Ｆ",
    "rating": 3.71,
    "ratingCount": 2359,
    "lat": 34.6546081180094,
    "lng": 135.50022730700508,
    "year": 2025,
    "award": "2025 ・ 百名店 ラーメン 大阪",
    "genre": "ラーメン"
  },
  {
    "rank": 60,
    "id": "27003232",
    "name": "らーめん弥七",
    "url": "https://tabelog.com/osaka/A2701/A270101/27003232/",
    "image": "https://tblg.k-img.com/restaurant/images/Rvw/38556/640x640_rect_38556746.jpg",
    "address": "大阪府大阪市北区豊崎3-4-8",
    "rating": 3.74,
    "ratingCount": 1947,
    "lat": 34.71130433716787,
    "lng": 135.49973727641634,
    "year": 2025,
    "award": "2025 ・ 百名店 ラーメン 大阪",
    "genre": "ラーメン"
  },
  {
    "rank": 61,
    "id": "27072765",
    "name": "麺のようじ",
    "url": "https://tabelog.com/osaka/A2701/A270202/27072765/",
    "image": "https://tblg.k-img.com/restaurant/images/Rvw/69567/640x640_rect_69567093.jpg",
    "address": "大阪府大阪市中央区高津2-1-2 大越ビル 1F",
    "rating": 3.71,
    "ratingCount": 1440,
    "lat": 34.66830217800424,
    "lng": 135.51130369713565,
    "year": 2025,
    "award": "2025 ・ 百名店 ラーメン 大阪",
    "genre": "ラーメン"
  },
  {
    "rank": 62,
    "id": "27120794",
    "name": "超多加水純手打ち麺 仁しむら",
    "url": "https://tabelog.com/osaka/A2707/A270703/27120794/",
    "image": "https://tblg.k-img.com/restaurant/images/Rvw/288688/640x640_rect_a1a413a64858a86a3cc2b6ffe0bcb118.jpg",
    "address": "大阪府東大阪市長堂1-28-14",
    "rating": 3.68,
    "ratingCount": 682,
    "lat": 34.66896693721527,
    "lng": 135.56414537594353,
    "year": 2025,
    "award": "2025 ・ 百名店 ラーメン 大阪",
    "genre": "ラーメン"
  },
  {
    "rank": 63,
    "id": "27077479",
    "name": "らーめん 小僧",
    "url": "https://tabelog.com/osaka/A2701/A270108/27077479/",
    "image": "https://tblg.k-img.com/restaurant/images/Rvw/211425/640x640_rect_3ba039ad63bc6aa2ed32a2a7401d3d8f.jpg",
    "address": "大阪府大阪市福島区福島3-8-10",
    "rating": 3.69,
    "ratingCount": 1387,
    "lat": 34.69354276797997,
    "lng": 135.4854389074087,
    "year": 2025,
    "award": "2025 ・ 百名店 ラーメン 大阪",
    "genre": "ラーメン"
  },
  {
    "rank": 64,
    "id": "27003934",
    "name": "麺厨房 華燕",
    "url": "https://tabelog.com/osaka/A2706/A270604/27003934/",
    "image": "https://tblg.k-img.com/restaurant/images/Rvw/232560/640x640_rect_d68ba04ba7a74bbb563daf717a64c0b5.jpg",
    "address": "大阪府高槻市牧田町7-54 109",
    "rating": 3.64,
    "ratingCount": 726,
    "lat": 34.82174750793614,
    "lng": 135.60347242862096,
    "year": 2025,
    "award": "2025 ・ 百名店 ラーメン 大阪",
    "genre": "ラーメン"
  },
  {
    "rank": 65,
    "id": "27102306",
    "name": "銀座 篝 ルクア大阪店",
    "url": "https://tabelog.com/osaka/A2701/A270101/27102306/",
    "image": "https://tblg.k-img.com/restaurant/images/Rvw/137599/640x640_rect_137599534.jpg",
    "address": "大阪府大阪市北区梅田3-1-3 ルクア B2F",
    "rating": 3.68,
    "ratingCount": 2181,
    "lat": 34.70304552797729,
    "lng": 135.4959844274973,
    "year": 2025,
    "award": "2025 ・ 百名店 ラーメン 大阪",
    "genre": "ラーメン"
  },
  {
    "rank": 66,
    "id": "27094184",
    "name": "麺と肉 だいつる 鶴橋店",
    "url": "https://tabelog.com/osaka/A2701/A270205/27094184/",
    "image": "https://tblg.k-img.com/restaurant/images/Rvw/131039/640x640_rect_131039545.jpg",
    "address": "大阪府大阪市天王寺区舟橋町18-3",
    "rating": 3.65,
    "ratingCount": 1087,
    "lat": 34.66614364801153,
    "lng": 135.52991695710077,
    "year": 2025,
    "award": "2025 ・ 百名店 ラーメン 大阪",
    "genre": "ラーメン"
  },
  {
    "rank": 67,
    "id": "27004096",
    "name": "豊中麺哲",
    "url": "https://tabelog.com/osaka/A2706/A270601/27004096/",
    "image": "https://tblg.k-img.com/restaurant/images/Rvw/367357/640x640_rect_277decd90149ac06113201001fb24f4b.jpg",
    "address": "大阪府豊中市岡上の町2-2-6",
    "rating": 3.69,
    "ratingCount": 808,
    "lat": 34.78483833791497,
    "lng": 135.46340572834634,
    "year": 2025,
    "award": "2025 ・ 百名店 ラーメン 大阪",
    "genre": "ラーメン"
  },
  {
    "rank": 68,
    "id": "27080479",
    "name": "大阪麺哲",
    "url": "https://tabelog.com/osaka/A2701/A270101/27080479/",
    "image": "https://tblg.k-img.com/restaurant/images/Rvw/154293/640x640_rect_154293885.jpg",
    "address": "大阪府大阪市北区曾根崎2-10-27",
    "rating": 3.71,
    "ratingCount": 2326,
    "lat": 34.700848637175156,
    "lng": 135.5017235763093,
    "year": 2025,
    "award": "2025 ・ 百名店 ラーメン 大阪",
    "genre": "ラーメン"
  },
  {
    "rank": 69,
    "id": "27080284",
    "name": "麺ファクトリー ジョーズ",
    "url": "https://tabelog.com/osaka/A2701/A270204/27080284/",
    "image": "https://tblg.k-img.com/restaurant/images/Rvw/284399/640x640_rect_72d654408bb1f62a36e7c9930ce29517.jpg",
    "address": "大阪府大阪市中央区上本町西2-1-11 楠本ビル 1F",
    "rating": 3.69,
    "ratingCount": 1059,
    "lat": 34.67329171800394,
    "lng": 135.52030921717972,
    "year": 2025,
    "award": "2025 ・ 百名店 ラーメン 大阪",
    "genre": "ラーメン"
  },
  {
    "rank": 70,
    "id": "27064584",
    "name": "人類みな麺類",
    "url": "https://tabelog.com/osaka/A2701/A270301/27064584/",
    "image": "https://tblg.k-img.com/restaurant/images/Rvw/259522/640x640_rect_aaf8da5952e6c4862f356fcc7d5c31fd.jpg",
    "address": "大阪府大阪市淀川区西中島1-12-15",
    "rating": 3.75,
    "ratingCount": 4921,
    "lat": 34.72546206669035,
    "lng": 135.49918048395008,
    "year": 2025,
    "award": "2025 ・ 百名店 ラーメン 大阪",
    "genre": "ラーメン"
  },
  {
    "rank": 71,
    "id": "27066822",
    "name": "布施 細見商店",
    "url": "https://tabelog.com/osaka/A2707/A270703/27066822/",
    "image": "https://tblg.k-img.com/restaurant/images/Rvw/320788/640x640_rect_eeda0159f1f634dd038e98b2c36c053d.jpg",
    "address": "大阪府東大阪市足代新町8-2",
    "rating": 3.67,
    "ratingCount": 795,
    "lat": 34.664308437217045,
    "lng": 135.5604122758991,
    "year": 2025,
    "award": "2025 ・ 百名店 ラーメン 大阪",
    "genre": "ラーメン"
  },
  {
    "rank": 72,
    "id": "27061072",
    "name": "麺屋 八海山",
    "url": "https://tabelog.com/osaka/A2706/A270604/27061072/",
    "image": "https://tblg.k-img.com/restaurant/images/Rvw/366075/640x640_rect_ce5c2b9833174cc9ef1e9e26cbaea710.jpg",
    "address": "大阪府高槻市芥川町1-14-9",
    "rating": 3.71,
    "ratingCount": 1028,
    "lat": 34.8534558679203,
    "lng": 135.6169839589318,
    "year": 2025,
    "award": "2025 ・ 百名店 ラーメン 大阪",
    "genre": "ラーメン"
  },
  {
    "rank": 73,
    "id": "27122790",
    "name": "中華蕎麦 福はら",
    "url": "https://tabelog.com/osaka/A2707/A270703/27122790/",
    "image": "https://tblg.k-img.com/restaurant/images/Rvw/367285/640x640_rect_0bce65147ef569d462063b84205bfba7.jpg",
    "address": "大阪府東大阪市俊徳町1-3-24",
    "rating": 3.67,
    "ratingCount": 625,
    "lat": 34.657557948030295,
    "lng": 135.5716929069848,
    "year": 2025,
    "award": "2025 ・ 百名店 ラーメン 大阪",
    "genre": "ラーメン"
  },
  {
    "rank": 74,
    "id": "27121916",
    "name": "魚々麺 園",
    "url": "https://tabelog.com/osaka/A2707/A270703/27121916/",
    "image": "https://tblg.k-img.com/restaurant/images/Rvw/366950/640x640_rect_b8d0ad748195038a51e1482a95c8b299.jpg",
    "address": "大阪府東大阪市足代南1-3-12",
    "rating": 3.7,
    "ratingCount": 531,
    "lat": 34.66113043721978,
    "lng": 135.5627105758654,
    "year": 2025,
    "award": "2025 ・ 百名店 ラーメン 大阪",
    "genre": "ラーメン"
  },
  {
    "rank": 75,
    "id": "27115366",
    "name": "らーめん久遠",
    "url": "https://tabelog.com/osaka/A2701/A270106/27115366/",
    "image": "https://tblg.k-img.com/restaurant/images/Rvw/367038/640x640_rect_de5d4cb51fb9484504f2051c112b68a8.jpg",
    "address": "大阪府大阪市中央区船場中央1-4-3 船場センタービル3号館 B2F",
    "rating": 3.7,
    "ratingCount": 926,
    "lat": 34.68193913718878,
    "lng": 135.50679897611477,
    "year": 2025,
    "award": "2025 ・ 百名店 ラーメン 大阪",
    "genre": "ラーメン"
  },
  {
    "rank": 76,
    "id": "27076936",
    "name": "KUCHE",
    "url": "https://tabelog.com/osaka/A2701/A270307/27076936/",
    "image": "https://tblg.k-img.com/restaurant/images/Rvw/364945/640x640_rect_404bd377b9e0d662612488a6a6d36484.jpg",
    "address": "大阪府大阪市東淀川区瑞光1-5-32",
    "rating": 3.69,
    "ratingCount": 724,
    "lat": 34.74800711796141,
    "lng": 135.53576827792358,
    "year": 2025,
    "award": "2025 ・ 百名店 ラーメン 大阪",
    "genre": "ラーメン"
  },
  {
    "rank": 77,
    "id": "27092383",
    "name": "京都 麺屋たけ井 阪急梅田店",
    "url": "https://tabelog.com/osaka/A2701/A270101/27092383/",
    "image": "https://tblg.k-img.com/restaurant/images/Rvw/198869/640x640_rect_44146760b3a72afacfcd686e7345e606.jpg",
    "address": "大阪府大阪市北区芝田1-1-2 阪急梅田駅改札内 2F",
    "rating": 3.7,
    "ratingCount": 3475,
    "lat": 34.705252357976555,
    "lng": 135.49808065751813,
    "year": 2025,
    "award": "2025 ・ 百名店 ラーメン 大阪",
    "genre": "ラーメン"
  },
  {
    "rank": 78,
    "id": "27052471",
    "name": "麺一盃",
    "url": "https://tabelog.com/osaka/A2701/A270302/27052471/",
    "image": "https://tblg.k-img.com/restaurant/images/Rvw/361085/640x640_rect_949899d6b442e4a415fa17bf167add04.jpg",
    "address": "大阪府大阪市西淀川区柏里2-1-25",
    "rating": 3.69,
    "ratingCount": 751,
    "lat": 34.71127161796362,
    "lng": 135.469456037599,
    "year": 2025,
    "award": "2025 ・ 百名店 ラーメン 大阪",
    "genre": "ラーメン"
  },
  {
    "rank": 79,
    "id": "27007792",
    "name": "麺座ぎん",
    "url": "https://tabelog.com/osaka/A2705/A270501/27007792/",
    "image": "https://tblg.k-img.com/restaurant/images/Rvw/5131/640x640_rect_5131171.jpg",
    "address": "大阪府堺市堺区北瓦町2-3-23",
    "rating": 3.65,
    "ratingCount": 1080,
    "lat": 34.5762099580538,
    "lng": 135.48326805622506,
    "year": 2025,
    "award": "2025 ・ 百名店 ラーメン 大阪",
    "genre": "ラーメン"
  },
  {
    "rank": 80,
    "id": "27088923",
    "name": "らーめん香澄 中崎町店",
    "url": "https://tabelog.com/osaka/A2701/A270101/27088923/",
    "image": "https://tblg.k-img.com/restaurant/images/Rvw/258899/640x640_rect_f0a92f62edf9906f765960697ad89f2c.jpg",
    "address": "大阪府大阪市北区中崎2-1-1 小川ビル 1F",
    "rating": 3.69,
    "ratingCount": 1222,
    "lat": 34.708527067977364,
    "lng": 135.50715654754487,
    "year": 2025,
    "award": "2025 ・ 百名店 ラーメン 大阪",
    "genre": "ラーメン"
  },
  {
    "rank": 81,
    "id": "27061274",
    "name": "麺や しき",
    "url": "https://tabelog.com/osaka/A2707/A270701/27061274/",
    "image": "https://tblg.k-img.com/restaurant/images/Rvw/366378/640x640_rect_6d0efc885840fe4151e6ba12b0ee23eb.jpg",
    "address": "大阪府守口市豊秀町2-1-3 エスポワール豊秀ワン1F",
    "rating": 3.69,
    "ratingCount": 1003,
    "lat": 34.738315697976844,
    "lng": 135.56492082780525,
    "year": 2025,
    "award": "2025 ・ 百名店 ラーメン 大阪",
    "genre": "ラーメン"
  },
  {
    "rank": 82,
    "id": "27018753",
    "name": "群青",
    "url": "https://tabelog.com/osaka/A2701/A270103/27018753/",
    "image": "https://tblg.k-img.com/restaurant/images/Rvw/301966/640x640_rect_4cc01fa63734dcf3914809be170e823e.jpg",
    "address": "大阪府大阪市北区天神橋6-3-26",
    "rating": 3.73,
    "ratingCount": 1462,
    "lat": 34.710040137172776,
    "lng": 135.51263437639454,
    "year": 2025,
    "award": "2025 ・ 百名店 ラーメン 大阪",
    "genre": "ラーメン"
  },
  {
    "rank": 83,
    "id": "27059898",
    "name": "烈火 本店",
    "url": "https://tabelog.com/osaka/A2706/A270601/27059898/",
    "image": "https://tblg.k-img.com/restaurant/images/Rvw/42013/640x640_rect_42013750.jpg",
    "address": "大阪府豊中市庄内東町2-2-14",
    "rating": 3.68,
    "ratingCount": 1342,
    "lat": 34.748965457941694,
    "lng": 135.47579025797532,
    "year": 2025,
    "award": "2025 ・ 百名店 ラーメン 大阪",
    "genre": "ラーメン"
  },
  {
    "rank": 84,
    "id": "27040424",
    "name": "時屋",
    "url": "https://tabelog.com/osaka/A2701/A270301/27040424/",
    "image": "https://tblg.k-img.com/restaurant/images/Rvw/43533/640x640_rect_43533448.jpg",
    "address": "大阪府大阪市淀川区西中島5-1-4 １Ｆ",
    "rating": 3.73,
    "ratingCount": 2420,
    "lat": 34.7283413779629,
    "lng": 135.50122769774916,
    "year": 2025,
    "award": "2025 ・ 百名店 ラーメン 大阪",
    "genre": "ラーメン"
  },
  {
    "rank": 85,
    "id": "27079112",
    "name": "鶏 soba 座銀 本店",
    "url": "https://tabelog.com/osaka/A2701/A270102/27079112/",
    "image": "https://tblg.k-img.com/restaurant/images/Rvw/361266/640x640_rect_fcbdc26d88a1f4fc0e6d168544bfc3a0.jpg",
    "address": "大阪府大阪市西区江戸堀1-19-2",
    "rating": 3.71,
    "ratingCount": 2262,
    "lat": 34.689621137985526,
    "lng": 135.49506440736238,
    "year": 2025,
    "award": "2025 ・ 百名店 ラーメン 大阪",
    "genre": "ラーメン"
  },
  {
    "rank": 86,
    "id": "27064101",
    "name": "中村商店 高槻本店",
    "url": "https://tabelog.com/osaka/A2706/A270604/27064101/",
    "image": "https://tblg.k-img.com/restaurant/images/Rvw/158170/640x640_rect_158170870.jpg",
    "address": "大阪府高槻市上田辺町4-14",
    "rating": 3.69,
    "ratingCount": 1408,
    "lat": 34.849862387922705,
    "lng": 135.6173935688952,
    "year": 2025,
    "award": "2025 ・ 百名店 ラーメン 大阪",
    "genre": "ラーメン"
  },
  {
    "rank": 87,
    "id": "27051582",
    "name": "らーめん工房 RISE",
    "url": "https://tabelog.com/osaka/A2707/A270705/27051582/",
    "image": "https://tblg.k-img.com/restaurant/images/Rvw/367306/640x640_rect_bd88aac09f8448cd0e2aa9b2ab615296.jpg",
    "address": "大阪府八尾市本町3-11-22",
    "rating": 3.68,
    "ratingCount": 560,
    "lat": 34.62784863725115,
    "lng": 135.5948208755067,
    "year": 2025,
    "award": "2025 ・ 百名店 ラーメン 大阪",
    "genre": "ラーメン"
  },
  {
    "rank": 88,
    "id": "27057392",
    "name": "みつ星製麺所 福島本店",
    "url": "https://tabelog.com/osaka/A2701/A270108/27057392/",
    "image": "https://tblg.k-img.com/restaurant/images/Rvw/362936/640x640_rect_87083b9f2eb002875159403196cb8e55.jpg",
    "address": "大阪府大阪市福島区福島7-17-21 ベルメゾン福島1F",
    "rating": 3.65,
    "ratingCount": 1156,
    "lat": 34.699544007976186,
    "lng": 135.4855198074693,
    "year": 2025,
    "award": "2025 ・ 百名店 ラーメン 大阪",
    "genre": "ラーメン"
  },
  {
    "rank": 89,
    "id": "27105320",
    "name": "NAKAGAWA わず",
    "url": "https://tabelog.com/osaka/A2701/A270307/27105320/",
    "image": "https://tblg.k-img.com/restaurant/images/Rvw/365438/640x640_rect_11458cefb99a8a69d394bffe097f2f79.jpg",
    "address": "大阪府大阪市東淀川区菅原6-24-12",
    "rating": 3.68,
    "ratingCount": 697,
    "lat": 34.74162153715513,
    "lng": 135.52020877670822,
    "year": 2025,
    "award": "2025 ・ 百名店 ラーメン 大阪",
    "genre": "ラーメン"
  },
  {
    "rank": 90,
    "id": "27041576",
    "name": "麺屋 一慶",
    "url": "https://tabelog.com/osaka/A2706/A270604/27041576/",
    "image": "https://tblg.k-img.com/restaurant/images/Rvw/203813/640x640_rect_a1142abaee6db15fb7d70617159badd9.jpg",
    "address": "大阪府茨木市竹橋町8-2 ホウキビル　１Ｆ",
    "rating": 3.69,
    "ratingCount": 806,
    "lat": 34.82009680792823,
    "lng": 135.575379288624,
    "year": 2025,
    "award": "2025 ・ 百名店 ラーメン 大阪",
    "genre": "ラーメン"
  },
  {
    "rank": 91,
    "id": "27092793",
    "name": "Ramen 辻",
    "url": "https://tabelog.com/osaka/A2701/A270104/27092793/",
    "image": "https://tblg.k-img.com/restaurant/images/Rvw/60548/640x640_rect_60548192.jpg",
    "address": "大阪府大阪市中央区鎗屋町1-1-10 山大ビル1F",
    "rating": 3.68,
    "ratingCount": 1788,
    "lat": 34.682830837191084,
    "lng": 135.51585937611745,
    "year": 2025,
    "award": "2025 ・ 百名店 ラーメン 大阪",
    "genre": "ラーメン"
  },
  {
    "rank": 92,
    "id": "27107953",
    "name": "鯛白湯らーめん ○de▽",
    "url": "https://tabelog.com/osaka/A2701/A270301/27107953/",
    "image": "https://tblg.k-img.com/restaurant/images/Rvw/364814/640x640_rect_81639012290f6379ab437d30e084b349.jpg",
    "address": "大阪府大阪市淀川区西宮原1-5-6",
    "rating": 3.7,
    "ratingCount": 1951,
    "lat": 34.73282460795779,
    "lng": 135.49412055779942,
    "year": 2025,
    "award": "2025 ・ 百名店 ラーメン 大阪",
    "genre": "ラーメン"
  },
  {
    "rank": 93,
    "id": "27124204",
    "name": "ZEN LABORATORY",
    "url": "https://tabelog.com/osaka/A2701/A270101/27124204/",
    "image": "https://tblg.k-img.com/restaurant/images/Rvw/170300/640x640_rect_61cded89910f4514d0eb034fd5531432.jpg",
    "address": "大阪府大阪市北区芝田1-11-5",
    "rating": 3.65,
    "ratingCount": 1271,
    "lat": 34.70753953716959,
    "lng": 135.4976288763798,
    "year": 2025,
    "award": "2025 ・ 百名店 ラーメン 大阪",
    "genre": "ラーメン"
  },
  {
    "rank": 94,
    "id": "27007813",
    "name": "自己流ラーメン綿麺",
    "url": "https://tabelog.com/osaka/A2708/A270801/27007813/",
    "image": "https://tblg.k-img.com/restaurant/images/Rvw/364758/640x640_rect_9d0a4dbe70ed69870733a955074aac5d.jpg",
    "address": "大阪府松原市松ヶ丘3-6-15",
    "rating": 3.67,
    "ratingCount": 819,
    "lat": 34.58376723726877,
    "lng": 135.56225187508426,
    "year": 2025,
    "award": "2025 ・ 百名店 ラーメン 大阪",
    "genre": "ラーメン"
  },
  {
    "rank": 95,
    "id": "27117861",
    "name": "らぁめん しゅき",
    "url": "https://tabelog.com/osaka/A2701/A270205/27117861/",
    "image": "https://tblg.k-img.com/restaurant/images/Rvw/222552/640x640_rect_9712c6cea06c6ebf39b025a8736d7da0.jpg",
    "address": "大阪府大阪市東成区東小橋3-14-10",
    "rating": 3.69,
    "ratingCount": 1449,
    "lat": 34.6667030372063,
    "lng": 135.5314752759436,
    "year": 2025,
    "award": "2025 ・ 百名店 ラーメン 大阪",
    "genre": "ラーメン"
  },
  {
    "rank": 96,
    "id": "27084754",
    "name": "麺屋 丈六 なんば店",
    "url": "https://tabelog.com/osaka/A2701/A270202/27084754/",
    "image": "https://tblg.k-img.com/restaurant/images/Rvw/183436/640x640_rect_7f6a43268f4707a96a6e29ea45a4a517.jpg",
    "address": "大阪府大阪市中央区難波千日前6-16",
    "rating": 3.73,
    "ratingCount": 2641,
    "lat": 34.66368029800512,
    "lng": 135.50486898709346,
    "year": 2025,
    "award": "2025 ・ 百名店 ラーメン 大阪",
    "genre": "ラーメン"
  },
  {
    "rank": 97,
    "id": "27097422",
    "name": "中華そば 桐麺 総本店",
    "url": "https://tabelog.com/osaka/A2701/A270302/27097422/",
    "image": "https://tblg.k-img.com/restaurant/images/Rvw/337814/640x640_rect_3aa50e2aa590a34325dfdfc628c60d1e.jpg",
    "address": "大阪府大阪市淀川区十三本町2-1-6",
    "rating": 3.73,
    "ratingCount": 2317,
    "lat": 34.72017013715623,
    "lng": 135.4808800765191,
    "year": 2025,
    "award": "2025 ・ 百名店 ラーメン 大阪",
    "genre": "ラーメン"
  },
  {
    "rank": 98,
    "id": "27112089",
    "name": "なにわ 麺次郎",
    "url": "https://tabelog.com/osaka/A2701/A270202/27112089/",
    "image": "https://tblg.k-img.com/restaurant/images/Rvw/250176/640x640_rect_b8a1e7f290e6569e5788554835cfc812.jpg",
    "address": "大阪府大阪市中央区難波4-1-17 近鉄大阪難波駅 改札内",
    "rating": 3.71,
    "ratingCount": 2065,
    "lat": 34.66710871800085,
    "lng": 135.49830174713267,
    "year": 2025,
    "award": "2025 ・ 百名店 ラーメン 大阪",
    "genre": "ラーメン"
  },
  {
    "rank": 99,
    "id": "27054613",
    "name": "麺や而今 大東本店",
    "url": "https://tabelog.com/osaka/A2707/A270704/27054613/",
    "image": "https://tblg.k-img.com/restaurant/images/Rvw/73067/640x640_rect_73067179.jpg",
    "address": "大阪府大東市灰塚6-7-9",
    "rating": 3.73,
    "ratingCount": 1364,
    "lat": 34.699123018015314,
    "lng": 135.6075398673795,
    "year": 2025,
    "award": "2025 ・ 百名店 ラーメン 大阪",
    "genre": "ラーメン"
  },
  {
    "rank": 100,
    "id": "27065090",
    "name": "らーめん香澄 阿波座本店",
    "url": "https://tabelog.com/osaka/A2701/A270105/27065090/",
    "image": "https://tblg.k-img.com/restaurant/images/Rvw/30456/640x640_rect_30456123.jpg",
    "address": "大阪府大阪市西区京町堀2-12-13",
    "rating": 3.72,
    "ratingCount": 1563,
    "lat": 34.68497698798666,
    "lng": 135.48936998731946,
    "year": 2025,
    "award": "2025 ・ 百名店 ラーメン 大阪",
    "genre": "ラーメン"
  }
]